CHANGES.rst
CONTRIBUTORS.rst
MANIFEST.in
README.rst
VERSION
setup.cfg
setup.py
docs/LICENSE.GPL
docs/LICENSE.rst
docs/index.rst
src/visaplan/__init__.py
src/visaplan.plone.groups.egg-info/PKG-INFO
src/visaplan.plone.groups.egg-info/SOURCES.txt
src/visaplan.plone.groups.egg-info/dependency_links.txt
src/visaplan.plone.groups.egg-info/entry_points.txt
src/visaplan.plone.groups.egg-info/namespace_packages.txt
src/visaplan.plone.groups.egg-info/not-zip-safe
src/visaplan.plone.groups.egg-info/requires.txt
src/visaplan.plone.groups.egg-info/top_level.txt
src/visaplan/plone/__init__.py
src/visaplan/plone/groups/__init__.py
src/visaplan/plone/groups/_base_pio.py
src/visaplan/plone/groups/_base_tools.py
src/visaplan/plone/groups/_idxnames.py
src/visaplan/plone/groups/base.py
src/visaplan/plone/groups/configure.zcml
src/visaplan/plone/groups/interfaces.py
src/visaplan/plone/groups/groupboard/__init__.py
src/visaplan/plone/groups/groupboard/ajax.zcml
src/visaplan/plone/groups/groupboard/board.pt
src/visaplan/plone/groups/groupboard/browser.py
src/visaplan/plone/groups/groupboard/configure.zcml
src/visaplan/plone/groups/groupboard/crumbs.py
src/visaplan/plone/groups/groupboard/fullpage.zcml
src/visaplan/plone/groups/groupboard/groupboard.pt
src/visaplan/plone/groups/groupboard/interface.py
src/visaplan/plone/groups/groupboard/new-thread.pt
src/visaplan/plone/groups/groupboard/oldcrumbs.py
src/visaplan/plone/groups/groupboard/thread-reply.pt
src/visaplan/plone/groups/groupboard/utils.py
src/visaplan/plone/groups/groupboard/sql/update-0001.sql
src/visaplan/plone/groups/groupdesktop/__init__.py
src/visaplan/plone/groups/groupdesktop/ajax.zcml
src/visaplan/plone/groups/groupdesktop/browser.py
src/visaplan/plone/groups/groupdesktop/configure.zcml
src/visaplan/plone/groups/groupdesktop/crumbs.py
src/visaplan/plone/groups/groupdesktop/fullpage.zcml
src/visaplan/plone/groups/groupdesktop/gdmacros.pt
src/visaplan/plone/groups/groupdesktop/group_administration_learning_progress_view.pt
src/visaplan/plone/groups/groupdesktop/group_administration_user_view.pt
src/visaplan/plone/groups/groupdesktop/group_administration_view.pt
src/visaplan/plone/groups/groupdesktop/interface.py
src/visaplan/plone/groups/groupdesktop/oldcrumbs.py
src/visaplan/plone/groups/groupdesktop/our-animations.pt
src/visaplan/plone/groups/groupdesktop/our-articles.pt
